agent/_init_.py
agent/sku-agent.py
skuagent-0.1.0.dist-info/METADATA
skuagent-0.1.0.dist-info/WHEEL
skuagent-0.1.0.dist-info/top_level.txt
skuagent-0.1.0.dist-info/RECORD
