Metadata-Version: 2.4
Name: skuagent
Version: 0.1.0
Summary: 查询sku信息的mcp服务端
Author-email: zk <zkazj8@gmail.com>
License: MIT
Requires-Python: >=3.13
Requires-Dist: httpx>=0.28.1
Requires-Dist: mcp[cli]>=1.11.0
Requires-Dist: pymysql>=1.1.1
Requires-Dist: DBUtils>=3.1.1
